Metadata-Version: 2.1
Name: pi-is-better
Version: 0.0.0
Summary: Example lib built with bazel
Home-page: https://gitlab.saicny.com/saic-ny/saicny_core
Author: Ryan Butler
Author-email: ryan.butler@samsung.com
License: UNKNOWN
Platform: UNKNOWN
